orchard_client/__init__.py
orchard_client-2.1.0.dist-info/LICENSE.txt
orchard_client-2.1.0.dist-info/METADATA
orchard_client-2.1.0.dist-info/WHEEL
orchard_client-2.1.0.dist-info/top_level.txt
orchard_client-2.1.0.dist-info/RECORD
