Metadata-Version: 2.1
Name: orchard-client
Version: 2.1.0
Summary: A Python client for the Orchard API
Home-page: UNKNOWN
Author: Akorlie Edward Tsastu
Author-email: edwardakorlie73@gmail.com
License: MIT
Keywords: orchard_client
Platform: UNKNOWN
Classifier: Development Status :: 5 - Production/Stable
Classifier: Intended Audience :: Developers
Classifier: Operating System :: Microsoft :: Windows :: Windows 10
Classifier: License :: OSI Approved :: MIT License
Classifier: Programming Language :: Python :: 3
Requires-Python: >=3.6
License-File: LICENSE.txt
Requires-Dist: requests
